rope_mcp_server/__init__.py
rope_mcp_server/offset.py
rope_mcp_server/refactoring.py
rope_mcp_server/rope_utils.py
rope_mcp_server/server.py
rope_mcp_server-0.1.2.dist-info/METADATA
rope_mcp_server-0.1.2.dist-info/WHEEL
rope_mcp_server-0.1.2.dist-info/entry_points.txt
rope_mcp_server-0.1.2.dist-info/RECORD
