Metadata-Version: 2.4
Name: rope-mcp-server
Version: 0.1.2
Summary: MCP server for Python refactoring via Rope library
Project-URL: Homepage, https://github.com/krystofbe/rope-mcp-server
Project-URL: Repository, https://github.com/krystofbe/rope-mcp-server
Author: Krystof
License: MIT
Keywords: claude,mcp,python,refactoring,rope
Classifier: Development Status :: 4 - Beta
Classifier: Intended Audience :: Developers
Classifier: License :: OSI Approved :: MIT License
Classifier: Programming Language :: Python :: 3.12
Classifier: Topic :: Software Development :: Code Generators
Requires-Python: >=3.12
Requires-Dist: fastmcp>=2.14.3
Requires-Dist: rope>=1.14.0
